pyintacct/__init__.py
pyintacct/client.py
pyintacct/exceptions.py
pyintacct/models/__init__.py
pyintacct/models/accounts_receivable.py
pyintacct/models/base.py
pyintacct/models/company.py
pyintacct/models/order_entry.py
pyintacct/models/purchasing.py
pyintacct-0.1.1.dist-info/LICENSE
pyintacct-0.1.1.dist-info/METADATA
pyintacct-0.1.1.dist-info/WHEEL
pyintacct-0.1.1.dist-info/top_level.txt
pyintacct-0.1.1.dist-info/RECORD
