Metadata-Version: 2.1
Name: pyintacct
Version: 0.1.1
Summary: Python SDK for Intacct
Home-page: https://github.com/red-coracle/pyintacct
Author: red-coracle
Author-email: 
License: MIT
Platform: UNKNOWN
Classifier: Development Status :: 3 - Alpha
Classifier: Intended Audience :: Developers
Classifier: License :: OSI Approved :: MIT License
Classifier: Natural Language :: English
Classifier: Operating System :: OS Independent
Classifier: Programming Language :: Python :: 3
Classifier: Programming Language :: Python :: 3.6
Classifier: Programming Language :: Python :: 3.7
Classifier: Programming Language :: Python :: 3.8
Classifier: Programming Language :: Python :: 3.9
Requires-Python: >=3.6.1
License-File: LICENSE
Requires-Dist: requests (<3.0,>=2.22)
Requires-Dist: jxmlease (>=1.0.3)
Requires-Dist: pydantic (<2.0.0,>=1.6.2)
